{
    "date": "2026-04-28",
    "positive_things": [
        "Braukt ar velo",
        "Bērni sagaida mājās",
        "Skaists  saulriets un stari mākoņos"
    ],
    "negative_things": [
        "Darbā nepabeidzām objektu Turaidā"
    ],
    "gratitude": [
        "Par ģimeni un sievas atbalstu"
    ],
    "emotions": [
        "noguris",
        "noraizējies",
        "priecīgs"
    ],
    "notes": "",
    "diary_entry": "Ļoti sāp galva. No rīta lietoju medikamentus un vakarā arī. pārāk liels nogurums. ķeros klāt programmēšanas uzdevumiem 4. nedēļa frontend.\n",
    "sync_status": "synced",
    "updated_at": "2026-04-28T18:40:26.378515",
    "id": "2026-04-28"
}